Metadata-Version: 2.1
Name: odoo14-addon-stock-move-location
Version: 14.0.1.4.3
Summary: This module allows to move all stock in a stock location to an other one.
Home-page: https://github.com/OCA/stock-logistics-warehouse
Author: Julius Network Solutions, BCIM, Camptocamp, Odoo Community Association (OCA)
Author-email: support@odoo-community.org
License: AGPL-3
Platform: UNKNOWN
Classifier: Programming Language :: Python
Classifier: Framework :: Odoo
Classifier: Framework :: Odoo :: 14.0
Classifier: License :: OSI Approved :: GNU Affero General Public License v3
Requires-Python: >=3.6
Requires-Dist: odoo <14.1dev,>=14.0a
